Metadata-Version: 1.2
Name: emtp
Version: 1.0
Summary: EMTP is a software package for .
Home-page: UNKNOWN
Author: Yeison Cardona
Author-email: yencardonaal@unal.edu.co
Maintainer: Yeison Cardona
Maintainer-email: yencardonaal@unal.edu.co
License: BSD License
Download-URL: https://bitbucket.org/GREDyP/emtp/
Platform: UNKNOWN
Classifier: Intended Audience :: Developers
Classifier: Topic :: Scientific/Engineering
Classifier: Topic :: Scientific/Engineering :: Mathematics
Classifier: Topic :: Software Development :: Libraries
Classifier: Topic :: Software Development :: Libraries :: Python Modules
